[
    {
        "Question_1": "Who comes up to Rachel looking for Charlie when Rachel see Joey kissing Charlie?",
        "Answer_1": "Ross",
        "Question_2": "Where is Ross when he is on a date with Charlie?",
        "Answer_2": "On a Manhatten rooftop"
    },
    {
        "Question_1": "Who comes up to Rachel looking for Charlie when Rachel see Joey kissing Charlie?",
        "Answer_1": "Ross",
        "Question_2": "what is Monica holding when Ross is talking to Charlie? ",
        "Answer_2": "A magazine "
    },
    {
        "Question_1": "Who comes up to Rachel looking for Charlie when Rachel see Joey kissing Charlie?",
        "Answer_1": "Ross",
        "Question_2": "What is Ross carrying when walking in the coffee shop?",
        "Answer_2": "Ross is carrying a suitcase."
    },
    {
        "Question_1": "Who comes up to Rachel looking for Charlie when Rachel see Joey kissing Charlie?",
        "Answer_1": "Ross",
        "Question_2": "How does Rachel react after Ross introduces Charlie?",
        "Answer_2": "Rachel avoids shaking hands with Charlie."
    },
    {
        "Question_1": "Who comes up to Rachel looking for Charlie when Rachel see Joey kissing Charlie?",
        "Answer_1": "Ross",
        "Question_2": "What color flowers on are the table when Ross is talking to Charlie?",
        "Answer_2": "Purple"
    },
    {
        "Question_1": "Who comes up to Rachel looking for Charlie when Rachel see Joey kissing Charlie?",
        "Answer_1": "Ross",
        "Question_2": "What did Dirk say his character won on his show when he was talking to Ross about playing a scientist?",
        "Answer_2": "Dirk said his character won a Nobel Peace Prize."
    },
    {
        "Question_1": "Who comes up to Rachel looking for Charlie when Rachel see Joey kissing Charlie?",
        "Answer_1": "Ross",
        "Question_2": "Where is Ross' drink before he gets up from the table?",
        "Answer_2": "On the table in front of him"
    },
    {
        "Question_1": "Who comes up to Rachel looking for Charlie when Rachel see Joey kissing Charlie?",
        "Answer_1": "Ross",
        "Question_2": "Who is looking for Ross when they walk into the cafe and ask Gunther for Ross?",
        "Answer_2": "Professor Wheeler is looking for Ross"
    },
    {
        "Question_1": "Who comes up to Rachel looking for Charlie when Rachel see Joey kissing Charlie?",
        "Answer_1": "Ross",
        "Question_2": "What is Ross holding before Joey makes a comment about science?",
        "Answer_2": "a plate of food"
    },
    {
        "Question_1": "Who comes up to Rachel looking for Charlie when Rachel see Joey kissing Charlie?",
        "Answer_1": "Ross",
        "Question_2": "What did Ross do after saying Rachel's brains are smaller than his?",
        "Answer_2": "Poured wine into a glass"
    },
    {
        "Question_1": "Who comes up to Rachel looking for Charlie when Rachel see Joey kissing Charlie?",
        "Answer_1": "Ross",
        "Question_2": "Who does Charlie want to wait for after Ross is ready to leave?",
        "Answer_2": "Professor Spafford."
    },
    {
        "Question_1": "Who comes up to Rachel looking for Charlie when Rachel see Joey kissing Charlie?",
        "Answer_1": "Ross",
        "Question_2": "Who did Ross go and talk to when he went to get more wine?",
        "Answer_2": "Rachel and Phoebe"
    },
    {
        "Question_1": "Who comes up to Rachel looking for Charlie when Rachel see Joey kissing Charlie?",
        "Answer_1": "Ross",
        "Question_2": "What does Ross pour when he goes to talk to Rachel and Phoebe at the bar?",
        "Answer_2": "More wine"
    },
    {
        "Question_1": "Who comes up to Rachel looking for Charlie when Rachel see Joey kissing Charlie?",
        "Answer_1": "Ross",
        "Question_2": "Where are Joey and Ross when he introduces him to Dirk",
        "Answer_2": "At a party"
    },
    {
        "Question_1": "Who comes up to Rachel looking for Charlie when Rachel see Joey kissing Charlie?",
        "Answer_1": "Ross",
        "Question_2": "What do Monica and Chandler engage in when Charlie is talking about Ross's paper?",
        "Answer_2": "Monica makes a bet with Chandler."
    },
    {
        "Question_1": "Who comes up to Rachel looking for Charlie when Rachel see Joey kissing Charlie?",
        "Answer_1": "Ross",
        "Question_2": "What impression did Ross do before coming to the party",
        "Answer_2": "Joan Rivers"
    },
    {
        "Question_1": "Who comes up to Rachel looking for Charlie when Rachel see Joey kissing Charlie?",
        "Answer_1": "Ross",
        "Question_2": "What did Charlie mention to Ross after he mentioned her working with Noble prize Albert Wintermeyer?",
        "Answer_2": "Ross was surprised to find out she dated Albert"
    },
    {
        "Question_1": "Who comes up to Rachel looking for Charlie when Rachel see Joey kissing Charlie?",
        "Answer_1": "Ross",
        "Question_2": "What did Ross pick up when he stood up?",
        "Answer_2": "His glass of wine"
    },
    {
        "Question_1": "Who comes up to Rachel looking for Charlie when Rachel see Joey kissing Charlie?",
        "Answer_1": "Ross",
        "Question_2": "What is Monica looking at when Ross walks into the coffee shop?",
        "Answer_2": "Monica is looking at a magazine."
    },
    {
        "Question_1": "Who comes up to Rachel looking for Charlie when Rachel see Joey kissing Charlie?",
        "Answer_1": "Ross",
        "Question_2": "What did the woman next to Ross do after Joey told her he was happy to meet her?",
        "Answer_2": "waved goodbye"
    }
]